sat_gt_fel_invoices_downloader/__init__.py
sat_gt_fel_invoices_downloader/actions.py
sat_gt_fel_invoices_downloader/main.py
sat_gt_fel_invoices_downloader/models.py
sat_gt_fel_invoices_downloader-0.5.13.dist-info/LICENSE
sat_gt_fel_invoices_downloader-0.5.13.dist-info/METADATA
sat_gt_fel_invoices_downloader-0.5.13.dist-info/WHEEL
sat_gt_fel_invoices_downloader-0.5.13.dist-info/top_level.txt
sat_gt_fel_invoices_downloader-0.5.13.dist-info/RECORD
