Metadata-Version: 2.1
Name: sat-gt-fel-invoices-downloader
Version: 0.5.13
Home-page: https://github.com/gt-banks-parser/banks-parser-base
Author: Carlos Simon
Author-email: dev@csimon.dev
Classifier: Programming Language :: Python :: 3.7
Classifier: Development Status :: 4 - Beta
Classifier: License :: OSI Approved :: GNU General Public License v3 (GPLv3)
Classifier: Operating System :: OS Independent
Classifier: Intended Audience :: Financial and Insurance Industry
Classifier: Intended Audience :: Information Technology
Classifier: Topic :: Office/Business :: Financial
Classifier: Topic :: Utilities
Requires-Python: >=3.7
License-File: LICENSE
Requires-Dist: requests
Requires-Dist: beautifulsoup4
Requires-Dist: lxml
